WinCap/__init__.py
WinCap/constants.py
WinCap/core.py
WinCap/input.py
WinCap/sound.py
WinCap/winapi.py
wicanap-0.1.0.dist-info/licenses/LICENSE
wicanap-0.1.0.dist-info/METADATA
wicanap-0.1.0.dist-info/WHEEL
wicanap-0.1.0.dist-info/top_level.txt
wicanap-0.1.0.dist-info/RECORD
