Metadata-Version: 2.4
Name: wicanap
Version: 0.1.0
Summary: Minimal 2D graphics library for Python using WinAPI and ctypes
Author-email: Amir <vozamir1208@gmail.com>
License: pixapi — Personal-Use License
Project-URL: Homepage, https://github.com/yourusername/wicanap
Project-URL: Repository, https://github.com/yourusername/wicanap
Project-URL: Documentation, https://github.com/yourusername/wicanap#readme
Keywords: graphics,2d,windows,canvas,ctypes,gdi,rendering
Classifier: Programming Language :: Python :: 3
Classifier: Operating System :: Microsoft :: Windows
Classifier: Topic :: Software Development :: Libraries
Classifier: Topic :: Games/Entertainment :: Arcade
Classifier: License :: Other/Proprietary License
Requires-Python: >=3.8
License-File: LICENSE
Dynamic: license-file
